git_repo_manager
