Metadata-Version: 1.0
Name: git-repo-manager
Version: 0.2.0
Summary: A simple library that helps you manage your git repos
Home-page: https://github.com/victorpantoja/git-repo-manager
Author: Victor Pantoja
Author-email: victor.pantoja@gmail.com
License: MIT
Keywords: git gitorius github manager repo repository repositories
Platform: UNKNOWN
Classifier: Development Status :: 4 - Beta
Classifier: Intended Audience :: Developers
Classifier: Programming Language :: Python
